{
  "bikes": [
    {
      "date_stolen": 1774359934,
      "description": null,
      "frame_colors": [
        "Black",
        "Green"
      ],
      "frame_model": "Talon",
      "id": 3354458,
      "is_stock_img": false,
      "large_img": "https://files.bikeindex.org/uploads/Pu/1011463/large_IMG_9738.jpeg",
      "location_found": null,
      "manufacturer_name": "Giant",
      "external_id": null,
      "registry_name": null,
      "registry_url": null,
      "serial": "Unknown",
      "status": "stolen",
      "stolen": true,
      "stolen_coordinates": [
        32.32,
        -90.17
      ],
      "stolen_location": "Jackson, MS 39202, US",
      "thumb": "https://files.bikeindex.org/uploads/Pu/1011463/small_IMG_9738.jpeg",
      "title": "2016 Giant Talon",
      "url": "https://bikeindex.org/bikes/3354458",
      "year": 2016,
      "propulsion_type_slug": "foot-pedal",
      "cycle_type_slug": "bike"
    },
    {
      "date_stolen": 1774155600,
      "description": null,
      "frame_colors": [
        "Black"
      ],
      "frame_model": null,
      "id": 3353491,
      "is_stock_img": false,
      "large_img": "https://files.bikeindex.org/uploads/Pu/1010931/large_IMG_3895.PNG",
      "location_found": null,
      "manufacturer_name": "Giant",
      "external_id": null,
      "registry_name": null,
      "registry_url": null,
      "serial": "Unknown",
      "status": "stolen",
      "stolen": true,
      "stolen_coordinates": [
        38.95,
        -92.33
      ],
      "stolen_location": "Columbia, MO 65201, US",
      "thumb": "https://files.bikeindex.org/uploads/Pu/1010931/small_IMG_3895.PNG",
      "title": "Giant",
      "url": "https://bikeindex.org/bikes/3353491",
      "year": null,
      "propulsion_type_slug": "foot-pedal",
      "cycle_type_slug": "bike"
    },
    {
      "date_stolen": 1774029600,
      "description": null,
      "frame_colors": [
        "Silver, gray or bare metal"
      ],
      "frame_model": "Trance",
      "id": 3354071,
      "is_stock_img": false,
      "large_img": "https://files.bikeindex.org/uploads/Pu/1011268/large_processed-6E86F661-B3D7-404A-B4E0-7FD92E3E40E5.jpeg",
      "location_found": null,
      "manufacturer_name": "Giant",
      "external_id": null,
      "registry_name": null,
      "registry_url": null,
      "serial": "GAGA17728",
      "status": "stolen",
      "stolen": true,
      "stolen_coordinates": [
        40.71,
        -111.85
      ],
      "stolen_location": "Salt Lake City, UT 84106, US",
      "thumb": "https://files.bikeindex.org/uploads/Pu/1011268/small_processed-6E86F661-B3D7-404A-B4E0-7FD92E3E40E5.jpeg",
      "title": "2021 Giant Trance",
      "url": "https://bikeindex.org/bikes/3354071",
      "year": 2021,
      "propulsion_type_slug": "foot-pedal",
      "cycle_type_slug": "bike"
    },
    {
      "date_stolen": 1777150800,
      "description": "",
      "frame_colors": [
        "Black",
        "Blue"
      ],
      "frame_model": "Revel 2",
      "id": 3352667,
      "is_stock_img": false,
      "large_img": null,
      "location_found": null,
      "manufacturer_name": "Giant",
      "external_id": null,
      "registry_name": null,
      "registry_url": null,
      "serial": "C41A3021",
      "status": "stolen",
      "stolen": true,
      "stolen_coordinates": [
        33.22,
        -97.1
      ],
      "stolen_location": "Denton 76209, TX 76209, US",
      "thumb": null,
      "title": "Giant Revel 2",
      "url": "https://bikeindex.org/bikes/3352667",
      "year": null,
      "propulsion_type_slug": "foot-pedal",
      "cycle_type_slug": "bike"
    },
    {
      "date_stolen": null,
      "description": null,
      "frame_colors": [
        "Blue"
      ],
      "frame_model": null,
      "id": 3352488,
      "is_stock_img": false,
      "large_img": null,
      "location_found": "Iowa City, IA 52245, United States",
      "manufacturer_name": "Giant",
      "external_id": null,
      "registry_name": null,
      "registry_url": null,
      "serial": "Hidden",
      "status": "found",
      "stolen": false,
      "stolen_coordinates": null,
      "stolen_location": null,
      "thumb": null,
      "title": "2023 Giant",
      "url": "https://bikeindex.org/bikes/3352488",
      "year": 2023,
      "propulsion_type_slug": "foot-pedal",
      "cycle_type_slug": "bike"
    },
    {
      "date_stolen": null,
      "description": "",
      "frame_colors": [
        "Silver, gray or bare metal"
      ],
      "frame_model": null,
      "id": 3360468,
      "is_stock_img": false,
      "large_img": null,
      "location_found": "Colorado Springs, CO 80920, United States",
      "manufacturer_name": "Giant",
      "external_id": null,
      "registry_name": null,
      "registry_url": null,
      "serial": "Hidden",
      "status": "found",
      "stolen": false,
      "stolen_coordinates": null,
      "stolen_location": null,
      "thumb": null,
      "title": "Giant",
      "url": "https://bikeindex.org/bikes/3360468",
      "year": null,
      "propulsion_type_slug": "foot-pedal",
      "cycle_type_slug": "bike"
    },
    {
      "date_stolen": 1773752400,
      "description": "Large metal pedals with white painted screws ",
      "frame_colors": [
        "Silver, gray or bare metal"
      ],
      "frame_model": "Toughroad slr 2",
      "id": 3351712,
      "is_stock_img": false,
      "large_img": "https://files.bikeindex.org/uploads/Pu/1009635/large_Afficher_les_photos_r%C3%A9centes.png",
      "location_found": null,
      "manufacturer_name": "Giant",
      "external_id": null,
      "registry_name": null,
      "registry_url": null,
      "serial": "Unknown",
      "status": "stolen",
      "stolen": true,
      "stolen_coordinates": [
        -37.8,
        144.97
      ],
      "stolen_location": "Carlton, 3053, AU",
      "thumb": "https://files.bikeindex.org/uploads/Pu/1009635/small_Afficher_les_photos_r%C3%A9centes.png",
      "title": "2022 Giant Toughroad slr 2",
      "url": "https://bikeindex.org/bikes/3351712",
      "year": 2022,
      "propulsion_type_slug": "foot-pedal",
      "cycle_type_slug": "bike"
    },
    {
      "date_stolen": 1773678244,
      "description": null,
      "frame_colors": [
        "Brown"
      ],
      "frame_model": "Talon 1",
      "id": 3351348,
      "is_stock_img": false,
      "large_img": null,
      "location_found": null,
      "manufacturer_name": "Giant",
      "external_id": null,
      "registry_name": null,
      "registry_url": null,
      "serial": "K34K31767",
      "status": "stolen",
      "stolen": true,
      "stolen_coordinates": [
        38.63,
        -90.22
      ],
      "stolen_location": "St Louis, MO 63103, US",
      "thumb": null,
      "title": "2022 Giant Talon 1",
      "url": "https://bikeindex.org/bikes/3351348",
      "year": 2022,
      "propulsion_type_slug": "pedal-assist-and-throttle",
      "cycle_type_slug": "bike"
    },
    {
      "date_stolen": 1773678244,
      "description": null,
      "frame_colors": [
        "Brown"
      ],
      "frame_model": "Talon 1",
      "id": 3351349,
      "is_stock_img": false,
      "large_img": null,
      "location_found": null,
      "manufacturer_name": "Giant",
      "external_id": null,
      "registry_name": null,
      "registry_url": null,
      "serial": "K34K31767",
      "status": "stolen",
      "stolen": true,
      "stolen_coordinates": [
        38.63,
        -90.22
      ],
      "stolen_location": "St Louis, MO 63103, US",
      "thumb": null,
      "title": "2022 Giant Talon 1",
      "url": "https://bikeindex.org/bikes/3351349",
      "year": 2022,
      "propulsion_type_slug": "pedal-assist-and-throttle",
      "cycle_type_slug": "bike"
    },
    {
      "date_stolen": 1773602170,
      "description": "",
      "frame_colors": [
        "Black"
      ],
      "frame_model": "Stance",
      "id": 3351086,
      "is_stock_img": false,
      "large_img": null,
      "location_found": null,
      "manufacturer_name": "Giant",
      "external_id": null,
      "registry_name": null,
      "registry_url": null,
      "serial": "G3FA22308",
      "status": "stolen",
      "stolen": true,
      "stolen_coordinates": null,
      "stolen_location": "US",
      "thumb": null,
      "title": "2021 Giant Stance",
      "url": "https://bikeindex.org/bikes/3351086",
      "year": 2021,
      "propulsion_type_slug": "foot-pedal",
      "cycle_type_slug": "bike"
    },
    {
      "date_stolen": 1773601952,
      "description": "",
      "frame_colors": [
        "Blue"
      ],
      "frame_model": "Stance",
      "id": 3351085,
      "is_stock_img": false,
      "large_img": null,
      "location_found": null,
      "manufacturer_name": "Giant",
      "external_id": null,
      "registry_name": null,
      "registry_url": null,
      "serial": "G2FA30198",
      "status": "stolen",
      "stolen": true,
      "stolen_coordinates": null,
      "stolen_location": "US",
      "thumb": null,
      "title": "2021 Giant Stance",
      "url": "https://bikeindex.org/bikes/3351085",
      "year": 2021,
      "propulsion_type_slug": "foot-pedal",
      "cycle_type_slug": "bike"
    },
    {
      "date_stolen": 1773601200,
      "description": "",
      "frame_colors": [
        "Blue"
      ],
      "frame_model": "Stance",
      "id": 3351084,
      "is_stock_img": false,
      "large_img": null,
      "location_found": null,
      "manufacturer_name": "Giant",
      "external_id": null,
      "registry_name": null,
      "registry_url": null,
      "serial": "G3FA22314",
      "status": "stolen",
      "stolen": true,
      "stolen_coordinates": [
        29.43,
        -98.49
      ],
      "stolen_location": "San Antonio, TX 78205, US",
      "thumb": null,
      "title": "2021 Giant Stance",
      "url": "https://bikeindex.org/bikes/3351084",
      "year": 2021,
      "propulsion_type_slug": "foot-pedal",
      "cycle_type_slug": "bike"
    },
    {
      "date_stolen": 1773586800,
      "description": "",
      "frame_colors": [
        "Black",
        "Green"
      ],
      "frame_model": "Stance 1",
      "id": 3351016,
      "is_stock_img": false,
      "large_img": null,
      "location_found": null,
      "manufacturer_name": "Giant",
      "external_id": null,
      "registry_name": null,
      "registry_url": null,
      "serial": "GX613266",
      "status": "stolen",
      "stolen": true,
      "stolen_coordinates": [
        48.48,
        7.99
      ],
      "stolen_location": "Offenburg, 77654, DE",
      "thumb": null,
      "title": "2017 Giant Stance 1",
      "url": "https://bikeindex.org/bikes/3351016",
      "year": 2017,
      "propulsion_type_slug": "foot-pedal",
      "cycle_type_slug": "bike"
    },
    {
      "date_stolen": 1773549248,
      "description": null,
      "frame_colors": [
        "Yellow or Gold"
      ],
      "frame_model": "Momentum Voya E+3",
      "id": 3350550,
      "is_stock_img": false,
      "large_img": null,
      "location_found": null,
      "manufacturer_name": "Giant",
      "external_id": null,
      "registry_name": null,
      "registry_url": null,
      "serial": "EBGE04453",
      "status": "stolen",
      "stolen": true,
      "stolen_coordinates": [
        37.85,
        -122.27
      ],
      "stolen_location": "Berkeley, CA 94703, US",
      "thumb": null,
      "title": "2025 Giant Momentum Voya E+3",
      "url": "https://bikeindex.org/bikes/3350550",
      "year": 2025,
      "propulsion_type_slug": "pedal-assist",
      "cycle_type_slug": "bike"
    },
    {
      "date_stolen": 1773453600,
      "description": "2022 model bought in 2026",
      "frame_colors": [
        "Silver, gray or bare metal"
      ],
      "frame_model": "Escape 2 Disc XL",
      "id": 3350309,
      "is_stock_img": false,
      "large_img": null,
      "location_found": null,
      "manufacturer_name": "Giant",
      "external_id": null,
      "registry_name": null,
      "registry_url": null,
      "serial": "K6HK89873",
      "status": "stolen",
      "stolen": true,
      "stolen_coordinates": [
        37.41,
        -122.17
      ],
      "stolen_location": "Stanford, CA 94305, US",
      "thumb": null,
      "title": "2022 Giant Escape 2 Disc XL",
      "url": "https://bikeindex.org/bikes/3350309",
      "year": 2022,
      "propulsion_type_slug": "foot-pedal",
      "cycle_type_slug": "bike"
    },
    {
      "date_stolen": 1773356251,
      "description": null,
      "frame_colors": [
        "Black"
      ],
      "frame_model": "Contend AR 3",
      "id": 3350055,
      "is_stock_img": false,
      "large_img": null,
      "location_found": null,
      "manufacturer_name": "Giant",
      "external_id": null,
      "registry_name": null,
      "registry_url": null,
      "serial": "K7GK87426",
      "status": "stolen",
      "stolen": true,
      "stolen_coordinates": [
        40.75,
        -74.0
      ],
      "stolen_location": "New York, NY 10001, US",
      "thumb": null,
      "title": "Giant Contend AR 3",
      "url": "https://bikeindex.org/bikes/3350055",
      "year": null,
      "propulsion_type_slug": "foot-pedal",
      "cycle_type_slug": "bike"
    },
    {
      "date_stolen": 1773337435,
      "description": null,
      "frame_colors": [
        "Silver, gray or bare metal"
      ],
      "frame_model": null,
      "id": 3349959,
      "is_stock_img": false,
      "large_img": "https://files.bikeindex.org/uploads/Pu/1008662/large_IMG_7723.jpeg",
      "location_found": null,
      "manufacturer_name": "Giant",
      "external_id": null,
      "registry_name": null,
      "registry_url": null,
      "serial": "GQ409915",
      "status": "stolen",
      "stolen": true,
      "stolen_coordinates": [
        53.44,
        -113.58
      ],
      "stolen_location": "Edmonton, T6R 0A3, CA",
      "thumb": "https://files.bikeindex.org/uploads/Pu/1008662/small_IMG_7723.jpeg",
      "title": "2026 Giant",
      "url": "https://bikeindex.org/bikes/3349959",
      "year": 2026,
      "propulsion_type_slug": "foot-pedal",
      "cycle_type_slug": "bike"
    },
    {
      "date_stolen": 1773284400,
      "description": "Rear brake not working. Schwalbe tyres. Underside of frame has dried tyre sealant (there because it is very difficult to remove). Tube tape starting to slip. ",
      "frame_colors": [
        "Black"
      ],
      "frame_model": "TCR Advanced 1 Disc-PC L Black Chrome",
      "id": 3352948,
      "is_stock_img": false,
      "large_img": "https://files.bikeindex.org/uploads/Pu/1010518/large_IMG_4295.jpeg",
      "location_found": null,
      "manufacturer_name": "Giant",
      "external_id": null,
      "registry_name": null,
      "registry_url": null,
      "serial": "G9HF02496",
      "status": "stolen",
      "stolen": true,
      "stolen_coordinates": [
        51.47,
        -0.35
      ],
      "stolen_location": "Isleworth, TW7 6HN, GB",
      "thumb": "https://files.bikeindex.org/uploads/Pu/1010518/small_IMG_4295.jpeg",
      "title": "2023 Giant TCR Advanced 1 Disc-PC L Black Chrome",
      "url": "https://bikeindex.org/bikes/3352948",
      "year": 2023,
      "propulsion_type_slug": "foot-pedal",
      "cycle_type_slug": "bike"
    },
    {
      "date_stolen": 1773214200,
      "description": null,
      "frame_colors": [
        "Black"
      ],
      "frame_model": "Talon 5",
      "id": 3349319,
      "is_stock_img": false,
      "large_img": "https://files.bikeindex.org/uploads/Pu/1008428/large_E36BFB6A-206C-438C-8257-AEEB89393A63.jpeg",
      "location_found": null,
      "manufacturer_name": "Giant",
      "external_id": null,
      "registry_name": null,
      "registry_url": null,
      "serial": "Unknown",
      "status": "stolen",
      "stolen": true,
      "stolen_coordinates": [
        42.4,
        -71.14
      ],
      "stolen_location": "Cambridge, MA 02140, US",
      "thumb": "https://files.bikeindex.org/uploads/Pu/1008428/small_E36BFB6A-206C-438C-8257-AEEB89393A63.jpeg",
      "title": "2025 Giant Talon 5",
      "url": "https://bikeindex.org/bikes/3349319",
      "year": 2025,
      "propulsion_type_slug": "foot-pedal",
      "cycle_type_slug": "bike"
    },
    {
      "date_stolen": null,
      "description": null,
      "frame_colors": [
        "Purple"
      ],
      "frame_model": "Giant",
      "id": 3348769,
      "is_stock_img": false,
      "large_img": null,
      "location_found": "Valmont rd, CO 80304-2916, United States",
      "manufacturer_name": "Giant",
      "external_id": null,
      "registry_name": null,
      "registry_url": null,
      "serial": "Hidden",
      "status": "found",
      "stolen": false,
      "stolen_coordinates": null,
      "stolen_location": null,
      "thumb": null,
      "title": "2024 Giant Giant",
      "url": "https://bikeindex.org/bikes/3348769",
      "year": 2024,
      "propulsion_type_slug": "foot-pedal",
      "cycle_type_slug": "bike"
    },
    {
      "date_stolen": null,
      "description": "",
      "frame_colors": [
        "Black",
        "Green"
      ],
      "frame_model": "revel",
      "id": 3348417,
      "is_stock_img": false,
      "large_img": null,
      "location_found": "palo alto, CA 94306, United States",
      "manufacturer_name": "Giant",
      "external_id": null,
      "registry_name": null,
      "registry_url": null,
      "serial": "Hidden",
      "status": "found",
      "stolen": false,
      "stolen_coordinates": null,
      "stolen_location": null,
      "thumb": null,
      "title": "2017 Giant revel",
      "url": "https://bikeindex.org/bikes/3348417",
      "year": 2017,
      "propulsion_type_slug": "foot-pedal",
      "cycle_type_slug": "bike"
    },
    {
      "date_stolen": 1773097200,
      "description": "Giant ATX Elite MTB (around 2017), white with black and blue accents. In great conditioned. Front and back wheel each have 2 orange spoke reflectors. Back wheel has a spoke (most likely removed). The pedals have a rusted/old-looking footcage",
      "frame_colors": [
        "White",
        "Blue",
        "Black"
      ],
      "frame_model": "Giant ATX Elite",
      "id": 3348260,
      "is_stock_img": false,
      "large_img": "https://files.bikeindex.org/uploads/Pu/1007463/large_WhatsApp_Image_2026-03-10_at_12.25.08_AMm.jpeg",
      "location_found": null,
      "manufacturer_name": "Giant",
      "external_id": null,
      "registry_name": null,
      "registry_url": null,
      "serial": "UNCERTAIN",
      "status": "stolen",
      "stolen": true,
      "stolen_coordinates": [
        42.33,
        -71.1
      ],
      "stolen_location": "Boston, MA 02120, US",
      "thumb": "https://files.bikeindex.org/uploads/Pu/1007463/small_WhatsApp_Image_2026-03-10_at_12.25.08_AMm.jpeg",
      "title": "2017 Giant Giant ATX Elite",
      "url": "https://bikeindex.org/bikes/3348260",
      "year": 2017,
      "propulsion_type_slug": "foot-pedal",
      "cycle_type_slug": "bike"
    },
    {
      "date_stolen": 1773050400,
      "description": null,
      "frame_colors": [
        "Black"
      ],
      "frame_model": "Tempt E+3",
      "id": 3348277,
      "is_stock_img": false,
      "large_img": "https://files.bikeindex.org/uploads/Pu/1007483/large_IMG_0323.jpeg",
      "location_found": null,
      "manufacturer_name": "Giant",
      "external_id": null,
      "registry_name": null,
      "registry_url": null,
      "serial": "E3HE32904",
      "status": "stolen",
      "stolen": true,
      "stolen_coordinates": [
        33.54,
        -111.96
      ],
      "stolen_location": "Paradise Valley, AZ 85253, US",
      "thumb": "https://files.bikeindex.org/uploads/Pu/1007483/small_IMG_0323.jpeg",
      "title": "2023 Giant Tempt E+3",
      "url": "https://bikeindex.org/bikes/3348277",
      "year": 2023,
      "propulsion_type_slug": "pedal-assist",
      "cycle_type_slug": "bike"
    },
    {
      "date_stolen": 1773020883,
      "description": null,
      "frame_colors": [
        "Purple"
      ],
      "frame_model": "Contend AR3",
      "id": 3348040,
      "is_stock_img": false,
      "large_img": "https://files.bikeindex.org/uploads/Pu/1007216/large_IMG_1155.JPG",
      "location_found": null,
      "manufacturer_name": "Giant",
      "external_id": null,
      "registry_name": null,
      "registry_url": null,
      "serial": "K5HK71024",
      "status": "stolen",
      "stolen": true,
      "stolen_coordinates": [
        39.99,
        -83.0
      ],
      "stolen_location": "Columbus, OH 43201, US",
      "thumb": "https://files.bikeindex.org/uploads/Pu/1007216/small_IMG_1155.JPG",
      "title": "2021 Giant Contend AR3",
      "url": "https://bikeindex.org/bikes/3348040",
      "year": 2021,
      "propulsion_type_slug": "foot-pedal",
      "cycle_type_slug": "bike"
    },
    {
      "date_stolen": 1772971200,
      "description": null,
      "frame_colors": [
        "Green"
      ],
      "frame_model": "Revolt 2",
      "id": 3351239,
      "is_stock_img": false,
      "large_img": null,
      "location_found": null,
      "manufacturer_name": "Giant",
      "external_id": null,
      "registry_name": null,
      "registry_url": null,
      "serial": "K1GK59109",
      "status": "stolen",
      "stolen": true,
      "stolen_coordinates": [
        34.01,
        -118.47
      ],
      "stolen_location": "Santa Monica, CA 90405, US",
      "thumb": null,
      "title": "2021 Giant Revolt 2",
      "url": "https://bikeindex.org/bikes/3351239",
      "year": 2021,
      "propulsion_type_slug": "foot-pedal",
      "cycle_type_slug": "bike"
    }
  ]
}